linearsolve/__init__.py
linearsolve-3.6.2.dist-info/LICENSE
linearsolve-3.6.2.dist-info/METADATA
linearsolve-3.6.2.dist-info/WHEEL
linearsolve-3.6.2.dist-info/top_level.txt
linearsolve-3.6.2.dist-info/RECORD
